model_mail/__init__.py
model_mail/library.py
model_mail/model_mail.py
model_mail/renderers.py
model_mail/templates/model_mail/email.html
model_mail/utils.py
django_model_mail-0.3.0.dist-info/LICENSE
django_model_mail-0.3.0.dist-info/WHEEL
django_model_mail-0.3.0.dist-info/METADATA
django_model_mail-0.3.0.dist-info/RECORD
