Metadata-Version: 2.1
Name: django-model-mail
Version: 0.3.0
Summary: Django package that helps to create emails from models (e.g. for admins' notifications)
Home-page: https://github.com/la1t/django-model-mail
License: MIT
Keywords: django-model-mail
Author: Anatoly Gusev
Author-email: gusev.tolia@yandex.ru
Requires-Python: >=3.7,<4.0
Classifier: Development Status :: 2 - Pre-Alpha
Classifier: Intended Audience :: Developers
Classifier: License :: OSI Approved :: MIT License
Classifier: Natural Language :: English
Classifier: Programming Language :: Python
Classifier: Programming Language :: Python :: 3
Classifier: Programming Language :: Python :: 3.6
Classifier: Programming Language :: Python :: 3.7
Classifier: Programming Language :: Python :: 3.8
Classifier: Programming Language :: Python :: 3.9
Classifier: Programming Language :: Python :: Implementation :: CPython
Classifier: Programming Language :: Python :: Implementation :: PyPy
Classifier: Topic :: Software Development
Requires-Dist: Django (>=3.0.0,<4.0.0)
Project-URL: Bug Tracker, https://github.com/la1t/django-model-mail/issues
Project-URL: Documentation, https://django-model-mail.readthedocs.io
Project-URL: Repository, https://github.com/la1t/django-model-mail
Project-URL: Source, https://github.com/la1t/django-model-mail
